README.md
setup.py
chainer_computational_cost/__init__.py
chainer_computational_cost/computational_cost_hook.py
chainer_computational_cost.egg-info/PKG-INFO
chainer_computational_cost.egg-info/SOURCES.txt
chainer_computational_cost.egg-info/dependency_links.txt
chainer_computational_cost.egg-info/requires.txt
chainer_computational_cost.egg-info/top_level.txt
chainer_computational_cost/cost_calculators/__init__.py
chainer_computational_cost/cost_calculators/activation.py
chainer_computational_cost/cost_calculators/array.py
chainer_computational_cost/cost_calculators/connection.py
chainer_computational_cost/cost_calculators/cost_calculators.py
chainer_computational_cost/cost_calculators/math.py
chainer_computational_cost/cost_calculators/normalization.py
chainer_computational_cost/cost_calculators/pooling.py