Metadata-Version: 1.0
Name: chainer-computational-cost
Version: 0.1.1
Summary: Chainer theoretical computational cost estimator
Home-page: UNKNOWN
Author: Daichi SUZUO
Author-email: suzuo@preferred.jp
License: MIT
Platform: UNKNOWN
